rdwatch_cli/__init__.py
rdwatch_cli/api/__init__.py
rdwatch_cli/api/image.py
rdwatch_cli/api/movie.py
rdwatch_cli/config.py
rdwatch_cli/exceptions.py
rdwatch_cli/validators.py
rdwatch_cli-0.0.5.dist-info/entry_points.txt
rdwatch_cli-0.0.5.dist-info/WHEEL
rdwatch_cli-0.0.5.dist-info/METADATA
rdwatch_cli-0.0.5.dist-info/RECORD
